README.md
setup.py
QuickCut/QuickCut.py
QuickCut/sponsor.jpg
QuickCut/style.css
QuickCut/test.py
QuickCut/languages/README.md
QuickCut/languages/create_ts.bat
QuickCut/languages/en.qm
QuickCut/languages/en.qph
QuickCut/languages/en.ts
QuickCut/languages/project.pro
QuickCut/misc/README_en.html
QuickCut/misc/README_zh.html
QuickCut/misc/icon.icns
QuickCut/misc/icon.ico
QuickCut/misc/icon_listning.icns
QuickCut/misc/icon_listning.ico
QuickCut/misc/assets/image-20200724211333904.png
QuickCut/misc/assets/image-20200725102850979.png
QuickCut/misc/assets/image-20200725103013287.png
QuickCut/misc/assets/image-20200725103107328.png
QuickCut/misc/assets/image-20200725103137457.png
QuickCut/misc/assets/image-20200725103228908.png
QuickCut/misc/assets/image-20200725103257140.png
QuickCut/misc/assets/image-20200725103322509.png
QuickCut/misc/assets/image-20200725103345859.png
QuickCut/misc/assets/image-20200725104724393.png
QuickCut/misc/assets/image-20200725104814559.png
QuickCut/misc/assets/image-20200725104901324.png
QuickCut/misc/assets/image-20200725105113317.png
QuickCut/misc/assets/image-20200725105214629.png
QuickCut/misc/assets/image-20200725105301248.png
QuickCut/misc/assets/image-20200725110050437.png
QuickCut/misc/assets/image-20200725110307123.png
QuickCut/misc/assets/image-20200726203040942.png
QuickCut/misc/assets/image-20200801204028907.png
QuickCut/misc/assets/image-20200801204230301.png
QuickCut/misc/assets/sponsor.jpg
QuickCut/languages/README.md
QuickCut/languages/create_ts.bat
QuickCut/languages/en.qm
QuickCut/languages/en.qph
QuickCut/languages/en.ts
QuickCut/languages/project.pro
QuickCut/misc/README_en.html
QuickCut/misc/README_zh.html
QuickCut/misc/assets/image-20200724211333904.png
QuickCut/misc/assets/image-20200725102850979.png
QuickCut/misc/assets/image-20200725103013287.png
QuickCut/misc/assets/image-20200725103107328.png
QuickCut/misc/assets/image-20200725103137457.png
QuickCut/misc/assets/image-20200725103228908.png
Quick_Cut.egg-info/PKG-INFO
Quick_Cut.egg-info/SOURCES.txt
Quick_Cut.egg-info/dependency_links.txt
Quick_Cut.egg-info/entry_points.txt
Quick_Cut.egg-info/requires.txt
Quick_Cut.egg-info/top_level.txt